{
  "languages": {
    "integration": [
      {
        "id": 1,
        "name": "HTML",
        "src": "/assets/languages/html.png"
      },
      {
        "id": 2,
        "name": "CSS",
        "src": "/assets/languages/css.png"
      },
      {
        "id": 3,
        "name": "SASS",
        "src": "/assets/languages/sass.png"
      },
      {
        "id": 4,
        "name": "TAILWIND",
        "src": "/assets/languages/tailwind.png"
      }
    ],
    "frontend": [
      {
        "id": 1,
        "name": "NEXTJS",
        "src": "/assets/languages/nextjs.png"
      },
      {
        "id": 2,
        "name": "REACT",
        "src": "/assets/languages/react.png"
      },
      {
        "id": 3,
        "name": "REDUX",
        "src": "/assets/languages/redux.png"
      },
      {
        "id": 4,
        "name": "JAVASCRIPT",
        "src": "/assets/languages/javascript.png"
      }
    ]
  },
  "carrousel": {
    "projects": [
      {
        "id": 1,
        "name": "KASA",
        "src": "/assets/images/kasa.png",
        "websiteLink": "https://jimmy-ctln.github.io/",
        "githubLink": "https://github.com/Jimmy-Ctln/Location-Immobiliere",
        "description": "Intégration d'une maquette responsive avec React et sass"
      },
      {
        "id": 2,
        "name": "Ohmyfood",
        "src": "/assets/images/ohmyfood.png",
        "websiteLink": "",
        "githubLink": "https://github.com/Jimmy-Ctln/Projet-4-ohmyfood.github.io",
        "description": "Ohmyfood est une entreprise de commande de repas en ligne."
      },
      {
        "id": 3,
        "name": "Argent-Bank",
        "src": "/assets/images/argent-bank.png",
        "websiteLink": "",
        "githubLink": "https://github.com/Jimmy-Ctln/ArgentBank-website",
        "description": "Argent Bank est une nouvelle banque en ligne qui souhaite percer dans le secteur bancaire."
      }
    ]
  }
}